setup.py
gauss_binom_pdf/Binomialdistribution.py
gauss_binom_pdf/Gaussiandistribution.py
gauss_binom_pdf/Generaldistribution.py
gauss_binom_pdf/__init__.py
gauss_binom_pdf.egg-info/PKG-INFO
gauss_binom_pdf.egg-info/SOURCES.txt
gauss_binom_pdf.egg-info/dependency_links.txt
gauss_binom_pdf.egg-info/not-zip-safe
gauss_binom_pdf.egg-info/top_level.txt